config_onion/__init__.py
config_onion-0.0.1.dist-info/LICENSE
config_onion-0.0.1.dist-info/METADATA
config_onion-0.0.1.dist-info/WHEEL
config_onion-0.0.1.dist-info/top_level.txt
config_onion-0.0.1.dist-info/RECORD
