Metadata-Version: 2.1
Name: config-onion
Version: 0.0.1
Summary: config_onion -  layered configuration, because configs are like ogres
Home-page: https://github.com/darviarush/python-config-onion
Author: Kosmina O. Yaroslav
Author-email: darviarush@mail.ru
License: MIT
Platform: any
Classifier: Development Status :: 4 - Beta
Classifier: Topic :: Text Processing
Classifier: License :: OSI Approved :: MIT License
Classifier: Operating System :: OS Independent
Classifier: Programming Language :: Python :: 3
Classifier: Programming Language :: Python :: 3.3
Classifier: Programming Language :: Python :: 3.4
Classifier: Programming Language :: Python :: 3.5
Classifier: Programming Language :: Python :: 3.6
Classifier: Programming Language :: Python :: 3.7
Requires-Python: >=3.6
